arxivscraper/__init__.py
arxivscraper/arxivscraper.py
arxivscraper/constants.py
arxivscraper/util.py
arxivscraper-0.0.6.dist-info/METADATA
arxivscraper-0.0.6.dist-info/WHEEL
arxivscraper-0.0.6.dist-info/licenses/LICENSE
arxivscraper-0.0.6.dist-info/RECORD
