Metadata-Version: 2.4
Name: arxivscraper
Version: 0.0.6
Author-email: mahdisadjadi <sadjadi.seyedmahdi@gmail.com>
License-File: LICENSE
Requires-Python: >=3.10
Requires-Dist: pip>=25.1.1
Requires-Dist: pytest>=8.4.1
